sdm/__init__.py
sdm/constants.py
sdm/master.py
sdm/api/__init__.py
sdm/api/api.py
sdm/api/fmp.py
sdm/api/iex_cloud.py
sdm/candlestick/__init__.py
sdm/candlestick/evaluate.py
sdm/candlestick/parameters.py
sdm/candlestick/pattern/__init__.py
sdm/candlestick/pattern/advanced_shapes.py
sdm/candlestick/pattern/basic_shapes.py
sdm/candlestick/pattern/trend.py
sdm/operation/__init__.py
sdm/operation/validation.py
sdm/persistence/__init__.py
sdm/persistence/csv_operator.py
sdm/persistence/file_operator.py
sdm/persistence/sql_operator.py
sdm/simulation/__init__.py
sdm/simulation/market.py
sdm/simulation/performance.py
sdm/simulation/trader.py
sdm/simulation/transaction.py
sdm/util/__init__.py
sdm/util/date_utils.py
sdm/util/io_utils.py
sdm/util/market_utils.py
sdm/util/misc_utils.py
sdmaster-1.0.8.dist-info/LICENSE
sdmaster-1.0.8.dist-info/METADATA
sdmaster-1.0.8.dist-info/WHEEL
sdmaster-1.0.8.dist-info/top_level.txt
sdmaster-1.0.8.dist-info/RECORD
