Metadata-Version: 2.1
Name: sdmaster
Version: 1.0.8
Summary: Stock Data Master
Home-page: https://github.com/RedrumSherlock/stockdatamaster
Author: Mike Wang
Author-email: wml816@gmail.com
License: MIT
Platform: UNKNOWN
Classifier: Programming Language :: Python :: 3
Classifier: License :: OSI Approved :: MIT License
Classifier: Operating System :: OS Independent
Requires-Python: >=3.5
License-File: LICENSE
Requires-Dist: pandas
Requires-Dist: plotly
Requires-Dist: matplotlib
Requires-Dist: numpy
Requires-Dist: pytz
